pinefarm/__init__.py
pinefarm/cli/__init__.py
pinefarm/cli/_base.py
pinefarm/cli/configs.py
pinefarm/cli/info.py
pinefarm/cli/install.py
pinefarm/cli/list.py
pinefarm/cli/merge.py
pinefarm/cli/run.py
pinefarm/cli/update.py
pinefarm/configs.py
pinefarm/confs/lhapdf.conf
pinefarm/external/__init__.py
pinefarm/external/integrability.py
pinefarm/external/interface.py
pinefarm/external/mg5/__init__.py
pinefarm/external/mg5/cuts_code/abscoscsmax.f
pinefarm/external/mg5/cuts_code/abscoscsmin.f
pinefarm/external/mg5/cuts_code/atlas_1jet_8tev_r06.f
pinefarm/external/mg5/cuts_code/atlas_2jet_7tev_r06_0005.f
pinefarm/external/mg5/cuts_code/atlas_2jet_7tev_r06_0510.f
pinefarm/external/mg5/cuts_code/atlas_2jet_7tev_r06_1015.f
pinefarm/external/mg5/cuts_code/atlas_2jet_7tev_r06_1520.f
pinefarm/external/mg5/cuts_code/atlas_2jet_7tev_r06_2025.f
pinefarm/external/mg5/cuts_code/atlas_2jet_7tev_r06_2530.f
pinefarm/external/mg5/cuts_code/atlas_dy3d_8tev.f
pinefarm/external/mg5/cuts_code/atlas_wzrap11_cf.f
pinefarm/external/mg5/cuts_code/cms_2jet_3d_8tev.f
pinefarm/external/mg5/cuts_code/cms_2jets_7tev_0005.f
pinefarm/external/mg5/cuts_code/cms_2jets_7tev_0510.f
pinefarm/external/mg5/cuts_code/cms_2jets_7tev_1015.f
pinefarm/external/mg5/cuts_code/cms_2jets_7tev_1520.f
pinefarm/external/mg5/cuts_code/cms_2jets_7tev_2025.f
pinefarm/external/mg5/cuts_code/dyjj.f
pinefarm/external/mg5/cuts_code/minetal.f
pinefarm/external/mg5/cuts_code/mjj.f
pinefarm/external/mg5/cuts_code/mmllmax.f
pinefarm/external/mg5/cuts_code/mtw.f
pinefarm/external/mg5/cuts_code/ptj1min.f
pinefarm/external/mg5/cuts_code/ptl1min.f
pinefarm/external/mg5/cuts_code/ptmiss.f
pinefarm/external/mg5/cuts_code/ptzmax.f
pinefarm/external/mg5/cuts_code/ptzmin.f
pinefarm/external/mg5/cuts_code/yh.f
pinefarm/external/mg5/cuts_code/yll.f
pinefarm/external/mg5/cuts_code/yt.f
pinefarm/external/mg5/cuts_code/yz.f
pinefarm/external/mg5/cuts_code/yzmin.f
pinefarm/external/mg5/cuts_variables/abscoscs.f
pinefarm-0.3.3.dist-info/LICENSE
pinefarm-0.3.3.dist-info/METADATA
pinefarm-0.3.3.dist-info/WHEEL
pinefarm-0.3.3.dist-info/entry_points.txt
pinefarm-0.3.3.dist-info/RECORD
