Metadata-Version: 2.1
Name: pinefarm
Version: 0.3.3
Summary: Generate PineAPPL grids from PineCards.
Home-page: https://github.com/NNPDF/runcards
Author: Alessandro Candido
Author-email: candido.ale@gmail.com
Requires-Python: >=3.9,<4.0
Classifier: License :: OSI Approved :: GNU General Public License v3 (GPLv3)
Classifier: Programming Language :: Python :: 3
Classifier: Programming Language :: Python :: 3.9
Classifier: Programming Language :: Python :: 3.10
Classifier: Programming Language :: Python :: 3.11
Classifier: Programming Language :: Python :: 3.12
Classifier: Programming Language :: Python :: 3.13
Classifier: Topic :: Scientific/Engineering :: Physics
Provides-Extra: complete
Provides-Extra: constraints
Provides-Extra: dis
Provides-Extra: vrap
Requires-Dist: PyYAML (>=6.0.0,<7.0.0)
Requires-Dist: appdirs (>=1.4.4,<2.0.0)
Requires-Dist: click (>=8.0.1,<9.0.0)
Requires-Dist: eko[box] (>=0.14.2,<0.15.0) ; (python_version < "3.13") and (extra == "vrap" or extra == "complete")
Requires-Dist: lhapdf-management (>=0.3,<0.4)
Requires-Dist: lz4 (>=4.0.2,<5.0.0)
Requires-Dist: more-itertools (>=8.10.0,<9.0.0)
Requires-Dist: pandas (>1.4)
Requires-Dist: pineappl (>=0.8.2,<0.9.0)
Requires-Dist: pkgconfig (>=1.5.5,<2.0.0)
Requires-Dist: pygit2 (>=1.12.0,<2.0.0)
Requires-Dist: requests (>=2.26.0,<3.0.0)
Requires-Dist: rich (>=12.5.1,<13.0.0)
Requires-Dist: tomli (>=2.0.1,<3.0.0)
Requires-Dist: yadism[box] (>=0.13.4,<0.14.0) ; (python_version < "3.13") and (extra == "dis" or extra == "complete")
Project-URL: Repository, https://github.com/NNPDF/runcards
